__init__.py
pyjschema/__init__.py
pyjschema/dump.py
pyjschema/load.py
pyjschema/number.py
pyjschema/string.py
pyjschema/validate.py
pyjschema/string/__init__.py
pyjschema/string/formatter.py
pyjschema-1.1.0.dist-info/LICENSE
pyjschema-1.1.0.dist-info/METADATA
pyjschema-1.1.0.dist-info/WHEEL
pyjschema-1.1.0.dist-info/top_level.txt
pyjschema-1.1.0.dist-info/RECORD
