Metadata-Version: 2.1
Name: pyjschema
Version: 1.1.0
Summary: A package for validating json according to a json schema, and type parsing it to python types.
Author-email: Yedidya Freundlich <yedidya03@gmail.com>
License: MIT License
Project-URL: Homepage, https://github.com/yedidya03/jschema
Classifier: License :: OSI Approved :: MIT License
Classifier: Programming Language :: Python
Classifier: Programming Language :: Python :: 3
Requires-Python: >=3.9
License-File: LICENSE
Requires-Dist: fqdn >=1.5.1
Provides-Extra: dev
Requires-Dist: pytest ; extra == 'dev'
Requires-Dist: pip-tools ; extra == 'dev'
